[
    {
        "id": 2,
        "food_name": "donut",
        "no_plates": 1,
        "stock": 29,
        "price": 61,
        "discount": 0
    },
    {
        "id": 3,
        "food_name": "cupcake",
        "no_plates": 1,
        "stock": 45,
        "price": 61,
        "discount": 0
    },
    {
        "id": 4,
        "food_name": "salad",
        "no_plates": 1,
        "stock": 43,
        "price": 99,
        "discount": 0
    },
    {
        "id": 5,
        "food_name": "Gimbab",
        "no_plates": 2,
        "stock": 689,
        "price": 90,
        "discount": 9.0
    }
]